LICENSE
MANIFEST.in
README.md
requirements.txt
setup.py
examples/update-wrapper.yml
update_wrapper.egg-info/PKG-INFO
update_wrapper.egg-info/SOURCES.txt
update_wrapper.egg-info/dependency_links.txt
update_wrapper.egg-info/entry_points.txt
update_wrapper.egg-info/requires.txt
update_wrapper.egg-info/top_level.txt
updatewrapper/__init__.py
updatewrapper/command.py
updatewrapper/host.py
updatewrapper/connection/__init__.py
updatewrapper/connection/ssh.py
updatewrapper/flavor/__init__.py
updatewrapper/flavor/debian.py
updatewrapper/flavor/redhat.py
updatewrapper/utils/__init__.py
updatewrapper/utils/display.py
updatewrapper/utils/file.py